{
    "clusters":  [
                     {
                         "cluster":  "?????-?????????",
                         "errors":  [
                                        "Артикул \u0027122 V ?????????\u0027 отсутствует в справочнике",
                                        "Артикул \u0027123 V ?????\u0027 отсутствует в справочнике"
                                    ],
                         "missing_products":  [
                                                  "122 V ?????????",
                                                  "123 V ?????"
                                              ],
                         "pallets":  [

                                     ]
                     },
                     {
                         "cluster":  "??????",
                         "errors":  [
                                        "Артикул \u0027106 ???????\u0027 отсутствует в справочнике",
                                        "Артикул \u0027115 ????\u0027 отсутствует в справочнике",
                                        "Артикул \u0027124 ??????????\u0027 отсутствует в справочнике",
                                        "Артикул \u0027401 ?????????\u0027 отсутствует в справочнике"
                                    ],
                         "missing_products":  [
                                                  "106 ???????",
                                                  "115 ????",
                                                  "124 ??????????",
                                                  "401 ?????????"
                                              ],
                         "pallets":  [

                                     ]
                     }
                 ],
    "success":  true
}
